itunes_app_scraper/__init__.py
itunes_app_scraper/scraper.py
itunes_app_scraper/util.py
itunes_app_scraper_dmi-0.9.6.dist-info/LICENSE
itunes_app_scraper_dmi-0.9.6.dist-info/METADATA
itunes_app_scraper_dmi-0.9.6.dist-info/WHEEL
itunes_app_scraper_dmi-0.9.6.dist-info/top_level.txt
itunes_app_scraper_dmi-0.9.6.dist-info/RECORD
