Metadata-Version: 2.1
Name: itunes-app-scraper-dmi
Version: 0.9.6
Summary: A lightweight iTunes App Store scraper
Home-page: https://github.com/digitalmethodsinitiative/itunes-app-scraper
Author: Digital Methods Initiative
Author-email: stijn.peeters@uva.nl
Classifier: Programming Language :: Python :: 3
Classifier: License :: OSI Approved :: MIT License
Classifier: Operating System :: OS Independent
Requires-Python: >=3.6
License-File: LICENSE
Requires-Dist: requests
